README.rst
setup.cfg
setup.py
limeade/__init__.py
limeade/_scan_helpers.py
limeade/mutating.py
limeade/refreshing.py
limeade/scanning.py
limeade.egg-info/PKG-INFO
limeade.egg-info/SOURCES.txt
limeade.egg-info/dependency_links.txt
limeade.egg-info/top_level.txt
limeade.egg-info/zip-safe