Metadata-Version: 1.1
Name: limeade
Version: 0.1.0
Summary: Library for hot reloading Python code at runtime
Home-page: https://github.com/CFSworks/limeade
Author: Sam Edwards
Author-email: CFSworks@gmail.com
License: BSD 3-Clause License
Platform: UNKNOWN
Classifier: Development Status :: 2 - Pre-Alpha
Classifier: Intended Audience :: Developers
Classifier: License :: OSI Approved :: BSD License
Classifier: Programming Language :: Python :: 3
Classifier: Topic :: Software Development
